{
  "updatedAt": 1779131896,
  "seasonStart": 1778803200,
  "seasonEnd": 1781395200,
  "seasonDays": 30,
  "market": {
    "price": 0.00006893,
    "change24h": -0.06,
    "volume24h": 7.6,
    "liquidity": 17547.84,
    "buys24h": 3,
    "sells24h": 0
  },
  "stats": {
    "totalTrades": 7,
    "totalBuys": 6,
    "totalSells": 1,
    "totalWallets": 4,
    "totalBuyVolume": 10.06,
    "totalSellVolume": 29.42,
    "prizePool": 0,
    "jackpotsHit": 0
  },
  "wallets": {
    "0x5237454dac7d259dd88b34ceb17e195dca0a3f4d": {
      "rank": 1,
      "fs": 18.41,
      "bV": 6.11,
      "sV": 0,
      "bC": 88684.3963,
      "sC": 0,
      "balC": 11419240.1793,
      "aw": 1,
      "hb": 1.0037,
      "n": 2,
      "ft": 1779112799,
      "lt": 1779112846
    },
    "0x05f6cef254ed90c2f1e51120aa8a48e2547f74f4": {
      "rank": 2,
      "fs": 10.27,
      "bV": 3.31,
      "sV": 0,
      "bC": 46999.1588,
      "sC": 0,
      "balC": 35503501.2191,
      "aw": 1,
      "hb": 1.034,
      "n": 3,
      "ft": 1778955383,
      "lt": 1779107802
    },
    "0x34ba7dcc4691b80be3cca15cc532b03d51de51d6": {
      "rank": 3,
      "fs": 1.97,
      "bV": 0.64,
      "sV": 0,
      "bC": 9060.9051,
      "sC": 0,
      "balC": 287488.8393,
      "aw": 1,
      "hb": 1.0233,
      "n": 1,
      "ft": 1779011023,
      "lt": 1779011023
    },
    "0xa542b8ca57781d4495dce5d71704bb0d4301123f": {
      "rank": 4,
      "fs": 0,
      "bV": 0,
      "sV": 29.42,
      "bC": 0,
      "sC": 405000,
      "balC": 0,
      "aw": 0,
      "hb": 1.0513,
      "n": 1,
      "ft": 1778866210,
      "lt": 1778866210
    }
  },
  "trades": [
    {
      "h": "0xcb5c382f914125678b91953a82eb77829b39dc7108e786e50505db8d1b3f510f",
      "t": 1779112846,
      "ty": "buy",
      "w": "0x5237454dac7d259dd88b34ceb17e195dca0a3f4d",
      "ctr": 43420.08,
      "usd": 2.99,
      "s": 1
    },
    {
      "h": "0xe398cfa269434f6f863d651b175b7ff5959e280be4327b39286d71a2216e98b8",
      "t": 1779112799,
      "ty": "buy",
      "w": "0x5237454dac7d259dd88b34ceb17e195dca0a3f4d",
      "ctr": 45264.32,
      "usd": 3.12,
      "s": 1
    },
    {
      "h": "0x076ef11b474c047629e3153568ae83af23513780903db6bc4653c48571421b79",
      "t": 1779107802,
      "ty": "buy",
      "w": "0x05f6cef254ed90c2f1e51120aa8a48e2547f74f4",
      "ctr": 10382.9,
      "usd": 0.72,
      "s": 1
    },
    {
      "h": "0x0fa514591e0a99edc16201bdef9deeee88b05f5fc1c6c316d739706231f230cf",
      "t": 1779020862,
      "ty": "buy",
      "w": "0x05f6cef254ed90c2f1e51120aa8a48e2547f74f4",
      "ctr": 13302.11,
      "usd": 0.94,
      "s": 1
    },
    {
      "h": "0x1ba9ea381d69aa866b4211d92f77b03af5a916956c5700625db8436e4cbc6675",
      "t": 1779011023,
      "ty": "buy",
      "w": "0x34ba7dcc4691b80be3cca15cc532b03d51de51d6",
      "ctr": 9060.91,
      "usd": 0.64,
      "s": 1
    },
    {
      "h": "0x988a7b829ca570bc344b88f3c687d292d864c4e514923375610ade04b5cc9a81",
      "t": 1778955383,
      "ty": "buy",
      "w": "0x05f6cef254ed90c2f1e51120aa8a48e2547f74f4",
      "ctr": 23314.15,
      "usd": 1.65,
      "s": 1
    },
    {
      "h": "0x3b91094e473adacd0210a52023e8194f000c5406cd428ce87767ad8efa86c8f3",
      "t": 1778866210,
      "ty": "sell",
      "w": "0xa542b8ca57781d4495dce5d71704bb0d4301123f",
      "ctr": 405000,
      "usd": 29.42,
      "s": 1
    }
  ],
  "jackpots": []
}