{
  "updatedAt": 1779041374,
  "seasonStart": 1778803200,
  "seasonEnd": 1781395200,
  "seasonDays": 30,
  "market": {
    "price": 0.00007099,
    "change24h": 0.37,
    "volume24h": 3.6,
    "liquidity": 18088.67,
    "buys24h": 3,
    "sells24h": 0
  },
  "stats": {
    "totalTrades": 4,
    "totalBuys": 3,
    "totalSells": 1,
    "totalWallets": 3,
    "totalBuyVolume": 3.23,
    "totalSellVolume": 29.42,
    "prizePool": 0,
    "jackpotsHit": 0
  },
  "wallets": {
    "0x05f6cef254ed90c2f1e51120aa8a48e2547f74f4": {
      "rank": 1,
      "fs": 7.91,
      "bV": 2.59,
      "sV": 0,
      "bC": 36616.2591,
      "sC": 0,
      "balC": 35494202.0141,
      "aw": 1,
      "hb": 1.0166,
      "n": 2,
      "ft": 1778955383,
      "lt": 1779020862
    },
    "0x34ba7dcc4691b80be3cca15cc532b03d51de51d6": {
      "rank": 2,
      "fs": 1.93,
      "bV": 0.64,
      "sV": 0,
      "bC": 9060.9051,
      "sC": 0,
      "balC": 287488.8393,
      "aw": 1,
      "hb": 1.0059,
      "n": 1,
      "ft": 1779011023,
      "lt": 1779011023
    },
    "0xa542b8ca57781d4495dce5d71704bb0d4301123f": {
      "rank": 3,
      "fs": 0,
      "bV": 0,
      "sV": 29.42,
      "bC": 0,
      "sC": 405000,
      "balC": 0,
      "aw": 0,
      "hb": 1.0338,
      "n": 1,
      "ft": 1778866210,
      "lt": 1778866210
    }
  },
  "trades": [
    {
      "h": "0x0fa514591e0a99edc16201bdef9deeee88b05f5fc1c6c316d739706231f230cf",
      "t": 1779020862,
      "ty": "buy",
      "w": "0x05f6cef254ed90c2f1e51120aa8a48e2547f74f4",
      "ctr": 13302.11,
      "usd": 0.94,
      "s": 1
    },
    {
      "h": "0x1ba9ea381d69aa866b4211d92f77b03af5a916956c5700625db8436e4cbc6675",
      "t": 1779011023,
      "ty": "buy",
      "w": "0x34ba7dcc4691b80be3cca15cc532b03d51de51d6",
      "ctr": 9060.91,
      "usd": 0.64,
      "s": 1
    },
    {
      "h": "0x988a7b829ca570bc344b88f3c687d292d864c4e514923375610ade04b5cc9a81",
      "t": 1778955383,
      "ty": "buy",
      "w": "0x05f6cef254ed90c2f1e51120aa8a48e2547f74f4",
      "ctr": 23314.15,
      "usd": 1.65,
      "s": 1
    },
    {
      "h": "0x3b91094e473adacd0210a52023e8194f000c5406cd428ce87767ad8efa86c8f3",
      "t": 1778866210,
      "ty": "sell",
      "w": "0xa542b8ca57781d4495dce5d71704bb0d4301123f",
      "ctr": 405000,
      "usd": 29.42,
      "s": 1
    }
  ],
  "jackpots": []
}